README.md
setup.py
xaib/__init__.py
xaib/additional.py
xaib/nbeats.py
xaib/sas.py
xaib/ssa.py
xaib.egg-info/PKG-INFO
xaib.egg-info/SOURCES.txt
xaib.egg-info/dependency_links.txt
xaib.egg-info/not-zip-safe
xaib.egg-info/requires.txt
xaib.egg-info/top_level.txt