Metadata-Version: 1.0
Name: xaib
Version: 0.0.1
Summary: Explainable AI In Business
Home-page: https://github.com/firmai/automated-time-series
Author: snowde
Author-email: d.snow@firmai.org
License: MIT
Platform: UNKNOWN
